[
 {
  "bulk_actions": 0,
  "dashboard": 0,
  "desk_access": 0,
  "disabled": 0,
  "docstatus": 0,
  "doctype": "Role",
  "form_sidebar": 0,
  "home_page": null,
  "is_custom": 0,
  "list_sidebar": 0,
  "modified": "2024-05-29 11:42:45.754667",
  "name": "Guest",
  "notifications": 0,
  "restrict_to_domain": null,
  "role_name": "Guest",
  "search_bar": 0,
  "timeline": 0,
  "two_factor_auth": 0,
  "view_switcher": 0
 },
 {
  "bulk_actions": 1,
  "dashboard": 1,
  "desk_access": 1,
  "disabled": 0,
  "docstatus": 0,
  "doctype": "Role",
  "form_sidebar": 1,
  "home_page": null,
  "is_custom": 0,
  "list_sidebar": 1,
  "modified": "2024-05-29 11:42:45.764599",
  "name": "Administrator",
  "notifications": 1,
  "restrict_to_domain": null,
  "role_name": "Administrator",
  "search_bar": 1,
  "timeline": 1,
  "two_factor_auth": 0,
  "view_switcher": 1
 },
 {
  "bulk_actions": 1,
  "dashboard": 1,
  "desk_access": 1,
  "disabled": 0,
  "docstatus": 0,
  "doctype": "Role",
  "form_sidebar": 1,
  "home_page": null,
  "is_custom": 0,
  "list_sidebar": 1,
  "modified": "2024-05-29 11:42:45.773247",
  "name": "Desk User",
  "notifications": 1,
  "restrict_to_domain": null,
  "role_name": "Desk User",
  "search_bar": 1,
  "timeline": 1,
  "two_factor_auth": 0,
  "view_switcher": 1
 },
 {
  "bulk_actions": 1,
  "dashboard": 1,
  "desk_access": 1,
  "disabled": 0,
  "docstatus": 0,
  "doctype": "Role",
  "form_sidebar": 1,
  "home_page": null,
  "is_custom": 0,
  "list_sidebar": 1,
  "modified": "2024-05-29 11:42:45.783464",
  "name": "System Manager",
  "notifications": 1,
  "restrict_to_domain": null,
  "role_name": "System Manager",
  "search_bar": 1,
  "timeline": 1,
  "two_factor_auth": 0,
  "view_switcher": 1
 },
 {
  "bulk_actions": 1,
  "dashboard": 1,
  "desk_access": 1,
  "disabled": 0,
  "docstatus": 0,
  "doctype": "Role",
  "form_sidebar": 1,
  "home_page": null,
  "is_custom": 0,
  "list_sidebar": 1,
  "modified": "2024-05-29 11:42:45.791869",
  "name": "All",
  "notifications": 1,
  "restrict_to_domain": null,
  "role_name": "All",
  "search_bar": 1,
  "timeline": 1,
  "two_factor_auth": 0,
  "view_switcher": 1
 },
 {
  "bulk_actions": 1,
  "dashboard": 1,
  "desk_access": 1,
  "disabled": 0,
  "docstatus": 0,
  "doctype": "Role",
  "form_sidebar": 1,
  "home_page": null,
  "is_custom": 0,
  "list_sidebar": 1,
  "modified": "2024-05-29 11:42:46.217233",
  "name": "Website Manager",
  "notifications": 1,
  "restrict_to_domain": null,
  "role_name": "Website Manager",
  "search_bar": 1,
  "timeline": 1,
  "two_factor_auth": 0,
  "view_switcher": 1
 },
 {
  "bulk_actions": 1,
  "dashboard": 1,
  "desk_access": 1,
  "disabled": 0,
  "docstatus": 0,
  "doctype": "Role",
  "form_sidebar": 1,
  "home_page": null,
  "is_custom": 0,
  "list_sidebar": 1,
  "modified": "2024-05-29 11:42:46.540136",
  "name": "Dashboard Manager",
  "notifications": 1,
  "restrict_to_domain": null,
  "role_name": "Dashboard Manager",
  "search_bar": 1,
  "timeline": 1,
  "two_factor_auth": 0,
  "view_switcher": 1
 },
 {
  "bulk_actions": 1,
  "dashboard": 1,
  "desk_access": 1,
  "disabled": 0,
  "docstatus": 0,
  "doctype": "Role",
  "form_sidebar": 1,
  "home_page": null,
  "is_custom": 0,
  "list_sidebar": 1,
  "modified": "2024-05-29 11:42:47.576311",
  "name": "Workspace Manager",
  "notifications": 1,
  "restrict_to_domain": null,
  "role_name": "Workspace Manager",
  "search_bar": 1,
  "timeline": 1,
  "two_factor_auth": 0,
  "view_switcher": 1
 },
 {
  "bulk_actions": 1,
  "dashboard": 1,
  "desk_access": 1,
  "disabled": 0,
  "docstatus": 0,
  "doctype": "Role",
  "form_sidebar": 1,
  "home_page": null,
  "is_custom": 0,
  "list_sidebar": 1,
  "modified": "2024-05-29 11:42:47.787710",
  "name": "Report Manager",
  "notifications": 1,
  "restrict_to_domain": null,
  "role_name": "Report Manager",
  "search_bar": 1,
  "timeline": 1,
  "two_factor_auth": 0,
  "view_switcher": 1
 },
 {
  "bulk_actions": 1,
  "dashboard": 1,
  "desk_access": 1,
  "disabled": 0,
  "docstatus": 0,
  "doctype": "Role",
  "form_sidebar": 1,
  "home_page": null,
  "is_custom": 0,
  "list_sidebar": 1,
  "modified": "2024-05-29 11:42:48.539905",
  "name": "Script Manager",
  "notifications": 1,
  "restrict_to_domain": null,
  "role_name": "Script Manager",
  "search_bar": 1,
  "timeline": 1,
  "two_factor_auth": 0,
  "view_switcher": 1
 },
 {
  "bulk_actions": 1,
  "dashboard": 1,
  "desk_access": 1,
  "disabled": 0,
  "docstatus": 0,
  "doctype": "Role",
  "form_sidebar": 1,
  "home_page": null,
  "is_custom": 0,
  "list_sidebar": 1,
  "modified": "2024-05-29 11:42:52.303642",
  "name": "Prepared Report User",
  "notifications": 1,
  "restrict_to_domain": null,
  "role_name": "Prepared Report User",
  "search_bar": 1,
  "timeline": 1,
  "two_factor_auth": 0,
  "view_switcher": 1
 },
 {
  "bulk_actions": 1,
  "dashboard": 1,
  "desk_access": 1,
  "disabled": 0,
  "docstatus": 0,
  "doctype": "Role",
  "form_sidebar": 1,
  "home_page": null,
  "is_custom": 0,
  "list_sidebar": 1,
  "modified": "2024-05-29 11:42:52.808895",
  "name": "Inbox User",
  "notifications": 1,
  "restrict_to_domain": null,
  "role_name": "Inbox User",
  "search_bar": 1,
  "timeline": 1,
  "two_factor_auth": 0,
  "view_switcher": 1
 },
 {
  "bulk_actions": 1,
  "dashboard": 1,
  "desk_access": 1,
  "disabled": 0,
  "docstatus": 0,
  "doctype": "Role",
  "form_sidebar": 1,
  "home_page": null,
  "is_custom": 0,
  "list_sidebar": 1,
  "modified": "2024-05-29 11:42:57.411155",
  "name": "Blogger",
  "notifications": 1,
  "restrict_to_domain": null,
  "role_name": "Blogger",
  "search_bar": 1,
  "timeline": 1,
  "two_factor_auth": 0,
  "view_switcher": 1
 },
 {
  "bulk_actions": 1,
  "dashboard": 1,
  "desk_access": 1,
  "disabled": 0,
  "docstatus": 0,
  "doctype": "Role",
  "form_sidebar": 1,
  "home_page": null,
  "is_custom": 0,
  "list_sidebar": 1,
  "modified": "2024-05-29 11:42:57.615751",
  "name": "Newsletter Manager",
  "notifications": 1,
  "restrict_to_domain": null,
  "role_name": "Newsletter Manager",
  "search_bar": 1,
  "timeline": 1,
  "two_factor_auth": 0,
  "view_switcher": 1
 },
 {
  "bulk_actions": 1,
  "dashboard": 1,
  "desk_access": 1,
  "disabled": 0,
  "docstatus": 0,
  "doctype": "Role",
  "form_sidebar": 1,
  "home_page": null,
  "is_custom": 0,
  "list_sidebar": 1,
  "modified": "2024-05-29 11:42:57.934997",
  "name": "Knowledge Base Editor",
  "notifications": 1,
  "restrict_to_domain": null,
  "role_name": "Knowledge Base Editor",
  "search_bar": 1,
  "timeline": 1,
  "two_factor_auth": 0,
  "view_switcher": 1
 },
 {
  "bulk_actions": 1,
  "dashboard": 1,
  "desk_access": 1,
  "disabled": 0,
  "docstatus": 0,
  "doctype": "Role",
  "form_sidebar": 1,
  "home_page": null,
  "is_custom": 0,
  "list_sidebar": 1,
  "modified": "2024-05-29 11:42:57.945964",
  "name": "Knowledge Base Contributor",
  "notifications": 1,
  "restrict_to_domain": null,
  "role_name": "Knowledge Base Contributor",
  "search_bar": 1,
  "timeline": 1,
  "two_factor_auth": 0,
  "view_switcher": 1
 },
 {
  "bulk_actions": 1,
  "dashboard": 1,
  "desk_access": 1,
  "disabled": 0,
  "docstatus": 0,
  "doctype": "Role",
  "form_sidebar": 1,
  "home_page": null,
  "is_custom": 0,
  "list_sidebar": 1,
  "modified": "2024-05-29 11:43:03.932128",
  "name": "Purchase User",
  "notifications": 1,
  "restrict_to_domain": null,
  "role_name": "Purchase User",
  "search_bar": 1,
  "timeline": 1,
  "two_factor_auth": 0,
  "view_switcher": 1
 },
 {
  "bulk_actions": 1,
  "dashboard": 1,
  "desk_access": 1,
  "disabled": 0,
  "docstatus": 0,
  "doctype": "Role",
  "form_sidebar": 1,
  "home_page": null,
  "is_custom": 0,
  "list_sidebar": 1,
  "modified": "2024-05-29 11:43:03.946322",
  "name": "Accounts User",
  "notifications": 1,
  "restrict_to_domain": null,
  "role_name": "Accounts User",
  "search_bar": 1,
  "timeline": 1,
  "two_factor_auth": 0,
  "view_switcher": 1
 },
 {
  "bulk_actions": 1,
  "dashboard": 1,
  "desk_access": 1,
  "disabled": 0,
  "docstatus": 0,
  "doctype": "Role",
  "form_sidebar": 1,
  "home_page": null,
  "is_custom": 0,
  "list_sidebar": 1,
  "modified": "2024-05-29 11:43:03.951809",
  "name": "Accounts Manager",
  "notifications": 1,
  "restrict_to_domain": null,
  "role_name": "Accounts Manager",
  "search_bar": 1,
  "timeline": 1,
  "two_factor_auth": 0,
  "view_switcher": 1
 },
 {
  "bulk_actions": 1,
  "dashboard": 1,
  "desk_access": 1,
  "disabled": 0,
  "docstatus": 0,
  "doctype": "Role",
  "form_sidebar": 1,
  "home_page": null,
  "is_custom": 0,
  "list_sidebar": 1,
  "modified": "2024-05-29 11:43:03.964091",
  "name": "Sales User",
  "notifications": 1,
  "restrict_to_domain": null,
  "role_name": "Sales User",
  "search_bar": 1,
  "timeline": 1,
  "two_factor_auth": 0,
  "view_switcher": 1
 },
 {
  "bulk_actions": 1,
  "dashboard": 1,
  "desk_access": 1,
  "disabled": 0,
  "docstatus": 0,
  "doctype": "Role",
  "form_sidebar": 1,
  "home_page": null,
  "is_custom": 0,
  "list_sidebar": 1,
  "modified": "2024-05-29 11:43:11.205270",
  "name": "Sales Master Manager",
  "notifications": 1,
  "restrict_to_domain": null,
  "role_name": "Sales Master Manager",
  "search_bar": 1,
  "timeline": 1,
  "two_factor_auth": 0,
  "view_switcher": 1
 },
 {
  "bulk_actions": 1,
  "dashboard": 1,
  "desk_access": 1,
  "disabled": 0,
  "docstatus": 0,
  "doctype": "Role",
  "form_sidebar": 1,
  "home_page": null,
  "is_custom": 0,
  "list_sidebar": 1,
  "modified": "2024-05-29 11:43:11.215153",
  "name": "Maintenance User",
  "notifications": 1,
  "restrict_to_domain": null,
  "role_name": "Maintenance User",
  "search_bar": 1,
  "timeline": 1,
  "two_factor_auth": 0,
  "view_switcher": 1
 },
 {
  "bulk_actions": 1,
  "dashboard": 1,
  "desk_access": 1,
  "disabled": 0,
  "docstatus": 0,
  "doctype": "Role",
  "form_sidebar": 1,
  "home_page": null,
  "is_custom": 0,
  "list_sidebar": 1,
  "modified": "2024-05-29 11:43:11.221452",
  "name": "Maintenance Manager",
  "notifications": 1,
  "restrict_to_domain": null,
  "role_name": "Maintenance Manager",
  "search_bar": 1,
  "timeline": 1,
  "two_factor_auth": 0,
  "view_switcher": 1
 },
 {
  "bulk_actions": 1,
  "dashboard": 1,
  "desk_access": 1,
  "disabled": 0,
  "docstatus": 0,
  "doctype": "Role",
  "form_sidebar": 1,
  "home_page": null,
  "is_custom": 0,
  "list_sidebar": 1,
  "modified": "2024-05-29 11:43:11.234700",
  "name": "Purchase Manager",
  "notifications": 1,
  "restrict_to_domain": null,
  "role_name": "Purchase Manager",
  "search_bar": 1,
  "timeline": 1,
  "two_factor_auth": 0,
  "view_switcher": 1
 },
 {
  "bulk_actions": 1,
  "dashboard": 1,
  "desk_access": 1,
  "disabled": 0,
  "docstatus": 0,
  "doctype": "Role",
  "form_sidebar": 1,
  "home_page": null,
  "is_custom": 0,
  "list_sidebar": 1,
  "modified": "2024-05-29 11:43:11.248606",
  "name": "Sales Manager",
  "notifications": 1,
  "restrict_to_domain": null,
  "role_name": "Sales Manager",
  "search_bar": 1,
  "timeline": 1,
  "two_factor_auth": 0,
  "view_switcher": 1
 },
 {
  "bulk_actions": 1,
  "dashboard": 1,
  "desk_access": 1,
  "disabled": 0,
  "docstatus": 0,
  "doctype": "Role",
  "form_sidebar": 1,
  "home_page": null,
  "is_custom": 0,
  "list_sidebar": 1,
  "modified": "2024-05-29 11:43:11.254393",
  "name": "Purchase Master Manager",
  "notifications": 1,
  "restrict_to_domain": null,
  "role_name": "Purchase Master Manager",
  "search_bar": 1,
  "timeline": 1,
  "two_factor_auth": 0,
  "view_switcher": 1
 },
 {
  "bulk_actions": 1,
  "dashboard": 1,
  "desk_access": 1,
  "disabled": 0,
  "docstatus": 0,
  "doctype": "Role",
  "form_sidebar": 1,
  "home_page": null,
  "is_custom": 0,
  "list_sidebar": 1,
  "modified": "2024-05-29 11:43:15.837498",
  "name": "Translator",
  "notifications": 1,
  "restrict_to_domain": null,
  "role_name": "Translator",
  "search_bar": 1,
  "timeline": 1,
  "two_factor_auth": 0,
  "view_switcher": 1
 },
 {
  "bulk_actions": 1,
  "dashboard": 1,
  "desk_access": 1,
  "disabled": 0,
  "docstatus": 0,
  "doctype": "Role",
  "form_sidebar": 1,
  "home_page": null,
  "is_custom": 0,
  "list_sidebar": 1,
  "modified": "2024-05-29 11:44:32.806976",
  "name": "State Head",
  "notifications": 1,
  "restrict_to_domain": null,
  "role_name": "State Head",
  "search_bar": 1,
  "timeline": 1,
  "two_factor_auth": 0,
  "view_switcher": 1
 },
 {
  "bulk_actions": 1,
  "dashboard": 1,
  "desk_access": 1,
  "disabled": 0,
  "docstatus": 0,
  "doctype": "Role",
  "form_sidebar": 1,
  "home_page": null,
  "is_custom": 0,
  "list_sidebar": 1,
  "modified": "2024-05-29 11:44:32.812477",
  "name": "State Placement Coordinator",
  "notifications": 1,
  "restrict_to_domain": null,
  "role_name": "State Placement Coordinator",
  "search_bar": 1,
  "timeline": 1,
  "two_factor_auth": 0,
  "view_switcher": 1
 },
 {
  "bulk_actions": 1,
  "dashboard": 1,
  "desk_access": 1,
  "disabled": 0,
  "docstatus": 0,
  "doctype": "Role",
  "form_sidebar": 1,
  "home_page": null,
  "is_custom": 0,
  "list_sidebar": 1,
  "modified": "2024-05-29 11:44:32.817737",
  "name": "Zonal Head",
  "notifications": 1,
  "restrict_to_domain": null,
  "role_name": "Zonal Head",
  "search_bar": 1,
  "timeline": 1,
  "two_factor_auth": 0,
  "view_switcher": 1
 },
 {
  "bulk_actions": 1,
  "dashboard": 1,
  "desk_access": 1,
  "disabled": 0,
  "docstatus": 0,
  "doctype": "Role",
  "form_sidebar": 1,
  "home_page": null,
  "is_custom": 0,
  "list_sidebar": 1,
  "modified": "2024-05-29 11:44:32.822936",
  "name": "Centre Head",
  "notifications": 1,
  "restrict_to_domain": null,
  "role_name": "Centre Head",
  "search_bar": 1,
  "timeline": 1,
  "two_factor_auth": 0,
  "view_switcher": 1
 },
 {
  "bulk_actions": 1,
  "dashboard": 1,
  "desk_access": 1,
  "disabled": 0,
  "docstatus": 0,
  "doctype": "Role",
  "form_sidebar": 1,
  "home_page": null,
  "is_custom": 0,
  "list_sidebar": 1,
  "modified": "2024-05-29 11:44:32.838077",
  "name": "Head Office (PMU)",
  "notifications": 1,
  "restrict_to_domain": null,
  "role_name": "Head Office (PMU)",
  "search_bar": 1,
  "timeline": 1,
  "two_factor_auth": 0,
  "view_switcher": 1
 },
 {
  "bulk_actions": 1,
  "dashboard": 1,
  "desk_access": 1,
  "disabled": 0,
  "docstatus": 0,
  "doctype": "Role",
  "form_sidebar": 1,
  "home_page": null,
  "is_custom": 0,
  "list_sidebar": 1,
  "modified": "2024-05-29 11:44:32.843941",
  "name": "Centre Placement Coordinator",
  "notifications": 1,
  "restrict_to_domain": null,
  "role_name": "Centre Placement Coordinator",
  "search_bar": 1,
  "timeline": 1,
  "two_factor_auth": 0,
  "view_switcher": 1
 },
 {
  "bulk_actions": 1,
  "dashboard": 1,
  "desk_access": 1,
  "disabled": 0,
  "docstatus": 0,
  "doctype": "Role",
  "form_sidebar": 1,
  "home_page": null,
  "is_custom": 0,
  "list_sidebar": 1,
  "modified": "2024-07-03 12:18:47.750177",
  "name": "Head Office - Assessment Officer",
  "notifications": 1,
  "restrict_to_domain": null,
  "role_name": "Head Office - Assessment Officer",
  "search_bar": 1,
  "timeline": 1,
  "two_factor_auth": 0,
  "view_switcher": 1
 }
]